README.md
setup.py
nbtest/ATest.py
nbtest/Enums.py
nbtest/Utils.py
nbtest/__init__.py
nbtest/_assertpyx.py
nbtest/assertpyx.py
nbtest/future2to3.py
nbtest/jsonT.py
nbtest/jsonpath.py
nbtest/threads.py
nbtest.egg-info/PKG-INFO
nbtest.egg-info/SOURCES.txt
nbtest.egg-info/dependency_links.txt
nbtest.egg-info/requires.txt
nbtest.egg-info/top_level.txt
nbtest.egg-info/zip-safe