Metadata-Version: 1.1
Name: nbtest
Version: 0.2.7
Summary: nbtest
Home-page: https://github.com/jayvee-yjw/nbtest
Author: jayvee-yjw
Author-email: gmkingyao001@gmail.com
License: UNKNOWN
Download-URL: https://github.com/jayvee-yjw/nbtest/archive/master.zip
Keywords: nbtest
Platform: UNKNOWN
